cz_git_jira_conventional.py
cz_git_jira_conventional-2.3.0.dist-info/LICENSE
cz_git_jira_conventional-2.3.0.dist-info/METADATA
cz_git_jira_conventional-2.3.0.dist-info/WHEEL
cz_git_jira_conventional-2.3.0.dist-info/top_level.txt
cz_git_jira_conventional-2.3.0.dist-info/RECORD
