Metadata-Version: 2.1
Name: cz-git-jira-conventional
Version: 2.3.0
Summary: Extend the commitizen tools to create conventional commits and README that link to Jira and Git.
Home-page: https://github.com/vuonglv1612/cz-git-jira-conventional
Author: Le Van Vuong
Author-email: it.vuonglv@gmail.com
License: MIT
Platform: UNKNOWN
License-File: LICENSE
Requires-Dist: commitizen
